README.rst
setup.cfg
setup.py
django_generic_file.egg-info/PKG-INFO
django_generic_file.egg-info/SOURCES.txt
django_generic_file.egg-info/dependency_links.txt
django_generic_file.egg-info/requires.txt
django_generic_file.egg-info/top_level.txt
genericfile/__init__.py
genericfile/admin.py
genericfile/forms.py
genericfile/meta.py
genericfile/models.py
genericfile/tests.py
genericfile/urls.py
genericfile/views.py
genericfile/migrations/0001_initial.py
genericfile/migrations/0002_auto_20150822_1407.py
genericfile/migrations/__init__.py
genericfile/static/genericfile/genericfile.css
genericfile/static/genericfile/genericfile.js
genericfile/templates/genericfile/filestore_form.html
genericfile/templatetags/__init__.py
genericfile/templatetags/genericfiletags.py