Metadata-Version: 1.1
Name: django-generic-file
Version: 0.0.2
Summary: Django Generic File
Home-page: https://github.com/djangothon/django-generic-file
Author: Rajiv Subramanian M
Author-email: rajiv.m1991@gmail.com
License: MIT
Download-URL: https://github.com/djangothon/django-generic-file/tarball/0.0.2
Keywords: fileupload,django,file,upload
Platform: UNKNOWN
Classifier: Programming Language :: Python
Classifier: Topic :: Software Development :: Libraries :: Python Modules
Classifier: Framework :: Django
Classifier: Environment :: Web Environment
Classifier: Programming Language :: Python :: 2
Classifier: Programming Language :: Python :: 2.7
Classifier: Programming Language :: Python :: 3
Classifier: Programming Language :: Python :: 3.3
Classifier: Programming Language :: Python :: 3.4
